proxy_ext/__init__.py
proxy_ext/proxy_ext.py
proxy_ext-2.0.4.dist-info/LICENSE
proxy_ext-2.0.4.dist-info/METADATA
proxy_ext-2.0.4.dist-info/WHEEL
proxy_ext-2.0.4.dist-info/top_level.txt
proxy_ext-2.0.4.dist-info/RECORD
