Metadata-Version: 2.1
Name: proxy-ext
Version: 2.0.4
Summary: A Python proxy extension.
Home-page: https://github.com/neoctobers/py_proxy_ext
Author: @neoctobers
Author-email: neoctobers@gmail.com
License: UNKNOWN
Platform: UNKNOWN
Classifier: Programming Language :: Python :: 3
Classifier: License :: OSI Approved :: MIT License
Classifier: Operating System :: OS Independent
Requires-Dist: list-ext
Requires-Dist: file-ext
Requires-Dist: ip-query
Requires-Dist: xprint
